caches/__init__.py
caches/core.py
caches/importer.py
caches/py.typed
caches/types.py
caches/backends/__init__.py
caches/backends/base.py
caches/backends/dummy.py
caches/backends/locmem.py
caches/backends/redis.py
async_caches-0.3.0.dist-info/LICENSE
async_caches-0.3.0.dist-info/METADATA
async_caches-0.3.0.dist-info/WHEEL
async_caches-0.3.0.dist-info/top_level.txt
async_caches-0.3.0.dist-info/RECORD
