Metadata-Version: 2.1
Name: async-caches
Version: 0.3.0
Summary: Caching library reimplementing django.core.cache with async support and type hints, inspired by encode/databases.
Home-page: https://github.com/rafalp/async-caches
Author: Rafał Pitoń
Author-email: kontakt@rpiton.com
License: BSD
Platform: any
Classifier: Development Status :: 4 - Beta
Classifier: Intended Audience :: Developers
Classifier: License :: OSI Approved :: BSD License
Classifier: Operating System :: OS Independent
Classifier: Programming Language :: Python
Classifier: Programming Language :: Python :: 3.6
Classifier: Programming Language :: Python :: 3.7
Classifier: Topic :: Software Development :: Libraries :: Python Modules
Requires-Dist: aioredis (>=1.2.0)
